{"1:1":{"root":null,"lemma":"أ","pos":"interrogative"},"1:2":{"root":"رأي","lemma":"رَأَى","pos":"verb"},"1:3":{"root":"كيف","lemma":"كَيْف","pos":"noun"},"1:4":{"root":"فعل","lemma":"فَعَلَ","pos":"verb"},"1:5":{"root":"ربب","lemma":"رَبّ","pos":"noun"},"1:6":{"root":"صحب","lemma":"أَصْحاب","pos":"noun"},"1:7":{"root":"فيل","lemma":"فِيل","pos":"noun"},"2:1":{"root":null,"lemma":"أ","pos":"interrogative"},"2:2":{"root":"جعل","lemma":"جَعَلَ","pos":"verb"},"2:3":{"root":"كيد","lemma":"كَيْد","pos":"noun"},"2:4":{"root":null,"lemma":"فِي","pos":"particle"},"2:5":{"root":"ضلل","lemma":"تَضْلِيل","pos":"noun"},"3:1":{"root":"رسل","lemma":"أَرْسَلَ","pos":"verb"},"3:2":{"root":null,"lemma":"عَلَى","pos":"particle"},"3:3":{"root":"طير","lemma":"طَيْر","pos":"noun"},"3:4":{"root":"أبل","lemma":"أَبابِيل","pos":"noun"},"4:1":{"root":"رمي","lemma":"رَمَى","pos":"verb"},"4:2":{"root":"حجر","lemma":"حِجارَة","pos":"noun"},"4:3":{"root":null,"lemma":"مِن","pos":"particle"},"4:4":{"root":"سجل","lemma":"سِجِّيل","pos":"noun"},"5:1":{"root":"جعل","lemma":"جَعَلَ","pos":"verb"},"5:2":{"root":"عصف","lemma":"عَصْف","pos":"noun"},"5:3":{"root":"أكل","lemma":"مَأْكُول","pos":"noun"}}