{"2:1":{"root":"قرأ","lemma":"قُرْءان","pos":"proper noun"},"2:2":{"root":"حكم","lemma":"حَكِيم","pos":"noun"},"3:1":{"root":null,"lemma":"إِنّ","pos":"particle"},"3:2":{"root":null,"lemma":"ل","pos":"emphasis"},"3:3":{"root":"رسل","lemma":"مُرْسَل","pos":"noun"},"4:1":{"root":null,"lemma":"عَلَى","pos":"particle"},"4:2":{"root":"صرط","lemma":"صِراط","pos":"noun"},"4:3":{"root":"قوم","lemma":"مُسْتَقِيم","pos":"noun"},"5:1":{"root":"نزل","lemma":"تَنزِيل","pos":"noun"},"5:2":{"root":"عزز","lemma":"عَزِيز","pos":"noun"},"5:3":{"root":"رحم","lemma":"رَحِيم","pos":"noun"},"6:1":{"root":"نذر","lemma":"أَنذَرَ","pos":"verb"},"6:2":{"root":"قوم","lemma":"قَوْم","pos":"noun"},"6:3":{"root":null,"lemma":"ما","pos":"negation"},"6:4":{"root":"نذر","lemma":"أَنذَرَ","pos":"verb"},"6:5":{"root":"أبو","lemma":"آباء","pos":"noun"},"6:6":{"root":null,"lemma":"ف","pos":"resumption"},"6:7":{"root":"غفل","lemma":"غافِل","pos":"noun"},"7:1":{"root":null,"lemma":"ل","pos":"emphasis"},"7:2":{"root":"حقق","lemma":"حَقَّ","pos":"verb"},"7:3":{"root":"قول","lemma":"قَوْل","pos":"noun"},"7:4":{"root":null,"lemma":"عَلَى","pos":"particle"},"7:5":{"root":"كثر","lemma":"أَكْثَر","pos":"noun"},"7:6":{"root":null,"lemma":"ف","pos":"resumption"},"7:7":{"root":null,"lemma":"لا","pos":"negation"},"7:8":{"root":"أمن","lemma":"آمَنَ","pos":"verb"},"8:1":{"root":null,"lemma":"إِنّ","pos":"particle"},"8:2":{"root":"جعل","lemma":"جَعَلَ","pos":"verb"},"8:3":{"root":null,"lemma":"فِي","pos":"particle"},"8:4":{"root":"عنق","lemma":"عُنُق","pos":"noun"},"8:5":{"root":"غلل","lemma":"غِلّ","pos":"noun"},"8:6":{"root":null,"lemma":"ف","pos":"conjunction"},"8:7":{"root":null,"lemma":"إِلَى","pos":"particle"},"8:8":{"root":"ذقن","lemma":"أَذْقان","pos":"noun"},"8:9":{"root":null,"lemma":"ف","pos":"resumption"},"8:10":{"root":"قمح","lemma":"مُقْمَح","pos":"noun"},"9:1":{"root":"جعل","lemma":"جَعَلَ","pos":"verb"},"9:2":{"root":null,"lemma":"مِن","pos":"particle"},"9:3":{"root":"بين","lemma":"بَيْن","pos":"noun"},"9:4":{"root":"يدي","lemma":"يَد","pos":"noun"},"9:5":{"root":"سدد","lemma":"سَدّ","pos":"noun"},"9:6":{"root":null,"lemma":"و","pos":"conjunction"},"9:7":{"root":"خلف","lemma":"خَلْف","pos":"noun"},"9:8":{"root":"سدد","lemma":"سَدّ","pos":"noun"},"9:9":{"root":"غشو","lemma":"أُغْشِيَتْ","pos":"verb"},"9:10":{"root":null,"lemma":"ف","pos":"resumption"},"9:11":{"root":null,"lemma":"لا","pos":"negation"},"9:12":{"root":"بصر","lemma":"أَبْصَرَ","pos":"verb"},"10:1":{"root":"سوي","lemma":"سَواء","pos":"noun"},"10:2":{"root":null,"lemma":"عَلَى","pos":"particle"},"10:3":{"root":"نذر","lemma":"أَنذَرَ","pos":"verb"},"10:4":{"root":null,"lemma":"أَم","pos":"conjunction"},"10:5":{"root":null,"lemma":"لَم","pos":"negation"},"10:6":{"root":"نذر","lemma":"أَنذَرَ","pos":"verb"},"10:7":{"root":null,"lemma":"لا","pos":"negation"},"10:8":{"root":"أمن","lemma":"آمَنَ","pos":"verb"},"11:1":{"root":null,"lemma":"إِنّ","pos":"particle"},"11:2":{"root":"نذر","lemma":"أَنذَرَ","pos":"verb"},"11:3":{"root":null,"lemma":"مَن","pos":"relative pronoun"},"11:4":{"root":"تبع","lemma":"اتَّبَعَ","pos":"verb"},"11:5":{"root":"ذكر","lemma":"ذِكْر","pos":"noun"},"11:6":{"root":"خشي","lemma":"خَشِيَ","pos":"verb"},"11:7":{"root":"رحم","lemma":"رَحْمٰن","pos":"noun"},"11:8":{"root":"غيب","lemma":"غَيْب","pos":"noun"},"11:9":{"root":"بشر","lemma":"بُشِّرَ","pos":"verb"},"11:10":{"root":"غفر","lemma":"مَغْفِرَة","pos":"noun"},"11:11":{"root":"أجر","lemma":"أَجْر","pos":"noun"},"11:12":{"root":"كرم","lemma":"كَرِيم","pos":"noun"},"12:1":{"root":null,"lemma":"إِنّ","pos":"particle"},"12:3":{"root":"حيي","lemma":"أَحْيا","pos":"verb"},"12:4":{"root":"موت","lemma":"مَيِّت","pos":"particle"},"12:5":{"root":"كتب","lemma":"كَتَبَ","pos":"verb"},"12:6":{"root":null,"lemma":"ما","pos":"relative pronoun"},"12:7":{"root":"قدم","lemma":"قَدَّمَ","pos":"verb"},"12:8":{"root":"أثر","lemma":"أَثَر","pos":"noun"},"12:9":{"root":"كلل","lemma":"كُلّ","pos":"noun"},"12:10":{"root":"شيأ","lemma":"شَىْء","pos":"noun"},"12:11":{"root":"حصي","lemma":"أَحْصَى","pos":"verb"},"12:12":{"root":null,"lemma":"فِي","pos":"particle"},"12:13":{"root":"أمم","lemma":"إِمام","pos":"noun"},"12:14":{"root":"بين","lemma":"مُبِين","pos":"noun"},"13:1":{"root":"ضرب","lemma":"ضَرَبَ","pos":"verb"},"13:2":{"root":null,"lemma":"ل","pos":"particle"},"13:3":{"root":"مثل","lemma":"مَثَل","pos":"noun"},"13:4":{"root":"صحب","lemma":"أَصْحاب","pos":"noun"},"13:5":{"root":"قري","lemma":"قَرْيَة","pos":"noun"},"13:6":{"root":null,"lemma":"إِذ","pos":"time adverb"},"13:7":{"root":"جيأ","lemma":"جاءَ","pos":"verb"},"13:8":{"root":"رسل","lemma":"مُرْسَل","pos":"noun"},"14:1":{"root":null,"lemma":"إِذ","pos":"time adverb"},"14:2":{"root":"رسل","lemma":"أَرْسَلَ","pos":"verb"},"14:3":{"root":null,"lemma":"إِلَى","pos":"particle"},"14:4":{"root":"ثني","lemma":"اثْنَيْن","pos":"noun"},"14:5":{"root":"كذب","lemma":"كَذَّبَ","pos":"verb"},"14:6":{"root":"عزز","lemma":"عَزَّزْ","pos":"verb"},"14:7":{"root":"ثلث","lemma":"ثالِث","pos":"noun"},"14:8":{"root":"قول","lemma":"قالَ","pos":"verb"},"14:9":{"root":null,"lemma":"إِنّ","pos":"particle"},"14:10":{"root":null,"lemma":"إِلَى","pos":"particle"},"14:11":{"root":"رسل","lemma":"مُرْسَل","pos":"noun"},"15:1":{"root":"قول","lemma":"قالَ","pos":"verb"},"15:2":{"root":null,"lemma":"ما","pos":"negation"},"15:4":{"root":null,"lemma":"إِلّا","pos":"restriction"},"15:5":{"root":"بشر","lemma":"بَشَر","pos":"noun"},"15:6":{"root":"مثل","lemma":"مِثْل","pos":"noun"},"15:7":{"root":null,"lemma":"و","pos":"conjunction"},"15:8":{"root":"نزل","lemma":"أَنزَلَ","pos":"verb"},"15:9":{"root":"رحم","lemma":"رَحْمٰن","pos":"noun"},"15:10":{"root":null,"lemma":"مِن","pos":"particle"},"15:11":{"root":"شيأ","lemma":"شَىْء","pos":"noun"},"15:12":{"root":null,"lemma":"إِن","pos":"negation"},"15:14":{"root":null,"lemma":"إِلّا","pos":"restriction"},"15:15":{"root":"كذب","lemma":"كَذَبَ","pos":"verb"},"16:1":{"root":"قول","lemma":"قالَ","pos":"verb"},"16:2":{"root":"ربب","lemma":"رَبّ","pos":"noun"},"16:3":{"root":"علم","lemma":"عَلِمَ","pos":"verb"},"16:4":{"root":null,"lemma":"إِنّ","pos":"particle"},"16:5":{"root":null,"lemma":"إِلَى","pos":"particle"},"16:6":{"root":"رسل","lemma":"مُرْسَل","pos":"noun"},"17:1":{"root":null,"lemma":"و","pos":"conjunction"},"17:2":{"root":null,"lemma":"عَلَى","pos":"particle"},"17:3":{"root":null,"lemma":"إِلّا","pos":"restriction"},"17:4":{"root":"بلغ","lemma":"بَلاغ","pos":"noun"},"17:5":{"root":"بين","lemma":"مُبِين","pos":"noun"},"18:1":{"root":"قول","lemma":"قالَ","pos":"verb"},"18:2":{"root":null,"lemma":"إِنّ","pos":"particle"},"18:3":{"root":"طير","lemma":"اطَّيَّرْ","pos":"verb"},"18:4":{"root":null,"lemma":"ب","pos":"particle"},"18:5":{"root":null,"lemma":"ل","pos":"emphasis"},"18:6":{"root":null,"lemma":"لَم","pos":"negation"},"18:7":{"root":"نهي","lemma":"انتَهَى","pos":"verb"},"18:8":{"root":"رجم","lemma":"رَجَمْ","pos":"verb"},"18:9":{"root":"مسس","lemma":"مَسَّ","pos":"verb"},"18:10":{"root":null,"lemma":"مِن","pos":"particle"},"18:11":{"root":"عذب","lemma":"عَذاب","pos":"noun"},"18:12":{"root":"ألم","lemma":"أَلِيم","pos":"noun"},"19:1":{"root":"قول","lemma":"قالَ","pos":"verb"},"19:2":{"root":"طير","lemma":"طائِر","pos":"noun"},"19:3":{"root":null,"lemma":"مَع","pos":"location adverb"},"19:4":{"root":null,"lemma":"أ","pos":"interrogative"},"19:5":{"root":"ذكر","lemma":"ذُكِّرَ","pos":"verb"},"19:6":{"root":null,"lemma":"بَل","pos":"retraction"},"19:8":{"root":"قوم","lemma":"قَوْم","pos":"noun"},"19:9":{"root":"سرف","lemma":"مُسْرِف","pos":"noun"},"20:1":{"root":"جيأ","lemma":"جاءَ","pos":"verb"},"20:2":{"root":null,"lemma":"مِن","pos":"particle"},"20:3":{"root":"قصو","lemma":"أَقْصا","pos":"noun"},"20:4":{"root":"مدن","lemma":"مَدِينَة","pos":"noun"},"20:5":{"root":"رجل","lemma":"رَجُل","pos":"noun"},"20:6":{"root":"سعي","lemma":"سَعَى","pos":"verb"},"20:7":{"root":"قول","lemma":"قالَ","pos":"verb"},"20:8":{"root":"قوم","lemma":"قَوْم","pos":"noun"},"20:9":{"root":"تبع","lemma":"اتَّبَعَ","pos":"verb"},"20:10":{"root":"رسل","lemma":"مُرْسَل","pos":"noun"},"21:1":{"root":"تبع","lemma":"اتَّبَعَ","pos":"verb"},"21:2":{"root":null,"lemma":"مَن","pos":"relative pronoun"},"21:3":{"root":null,"lemma":"لا","pos":"negation"},"21:4":{"root":"سأل","lemma":"سَأَلَ","pos":"verb"},"21:5":{"root":"أجر","lemma":"أَجْر","pos":"noun"},"21:6":{"root":null,"lemma":"و","pos":"conjunction"},"21:7":{"root":"هدي","lemma":"مُهْتَدي","pos":"noun"},"22:1":{"root":null,"lemma":"و","pos":"conjunction"},"22:2":{"root":null,"lemma":"ل","pos":"particle"},"22:3":{"root":null,"lemma":"لا","pos":"negation"},"22:4":{"root":"عبد","lemma":"عَبَدَ","pos":"verb"},"22:5":{"root":null,"lemma":"الَّذِي","pos":"relative pronoun"},"22:6":{"root":"فطر","lemma":"فَطَرَ","pos":"verb"},"22:7":{"root":null,"lemma":"و","pos":"conjunction"},"22:8":{"root":"رجع","lemma":"رَجَعَ","pos":"verb"},"23:1":{"root":"أخذ","lemma":"اتَّخَذَ","pos":"verb"},"23:2":{"root":null,"lemma":"مِن","pos":"particle"},"23:3":{"root":"دون","lemma":"دُون","pos":"noun"},"23:4":{"root":"أله","lemma":"إِلٰه","pos":"noun"},"23:5":{"root":null,"lemma":"إِن","pos":"conditional"},"23:6":{"root":"رود","lemma":"أَرادَ","pos":"verb"},"23:7":{"root":"رحم","lemma":"رَحْمٰن","pos":"noun"},"23:8":{"root":"ضرر","lemma":"ضُرّ","pos":"noun"},"23:9":{"root":null,"lemma":"لا","pos":"negation"},"23:10":{"root":"غني","lemma":"أَغْنَتْ","pos":"verb"},"23:11":{"root":null,"lemma":"عَن","pos":"particle"},"23:12":{"root":"شفع","lemma":"شَفاعَة","pos":"noun"},"23:13":{"root":"شيأ","lemma":"شَىْء","pos":"noun"},"23:14":{"root":null,"lemma":"و","pos":"conjunction"},"23:15":{"root":"نقذ","lemma":"أَنقَذَ","pos":"verb"},"24:1":{"root":null,"lemma":"إِنّ","pos":"particle"},"24:2":{"root":null,"lemma":"إِذًا","pos":"answer"},"24:3":{"root":null,"lemma":"ل","pos":"emphasis"},"24:4":{"root":"ضلل","lemma":"ضَلال","pos":"noun"},"24:5":{"root":"بين","lemma":"مُبِين","pos":"noun"},"25:1":{"root":null,"lemma":"إِنّ","pos":"particle"},"25:2":{"root":"أمن","lemma":"آمَنَ","pos":"verb"},"25:3":{"root":"ربب","lemma":"رَبّ","pos":"noun"},"25:4":{"root":"سمع","lemma":"سَمِعَ","pos":"verb"},"26:1":{"root":"قول","lemma":"قالَ","pos":"verb"},"26:2":{"root":"دخل","lemma":"دَخَلَ","pos":"verb"},"26:3":{"root":"جنن","lemma":"جَنَّة","pos":"proper noun"},"26:4":{"root":"قول","lemma":"قالَ","pos":"verb"},"26:5":{"root":null,"lemma":"ي","pos":"vocative"},"26:6":{"root":"قوم","lemma":"قَوْم","pos":"noun"},"26:7":{"root":"علم","lemma":"عَلِمَ","pos":"verb"},"27:1":{"root":null,"lemma":"ب","pos":"particle"},"27:2":{"root":"غفر","lemma":"غَفَرَ","pos":"verb"},"27:3":{"root":null,"lemma":"ل","pos":"particle"},"27:4":{"root":"ربب","lemma":"رَبّ","pos":"noun"},"27:5":{"root":"جعل","lemma":"جَعَلَ","pos":"verb"},"27:6":{"root":null,"lemma":"مِن","pos":"particle"},"27:7":{"root":"كرم","lemma":"مُكْرَم","pos":"noun"},"28:1":{"root":null,"lemma":"و","pos":"conjunction"},"28:2":{"root":"نزل","lemma":"أَنزَلَ","pos":"verb"},"28:3":{"root":null,"lemma":"عَلَى","pos":"particle"},"28:4":{"root":"قوم","lemma":"قَوْم","pos":"noun"},"28:5":{"root":null,"lemma":"مِن","pos":"particle"},"28:6":{"root":"بعد","lemma":"بَعْد","pos":"noun"},"28:7":{"root":null,"lemma":"مِن","pos":"particle"},"28:8":{"root":"جند","lemma":"جُند","pos":"noun"},"28:9":{"root":null,"lemma":"مِن","pos":"particle"},"28:10":{"root":"سمو","lemma":"سَماء","pos":"noun"},"28:11":{"root":null,"lemma":"و","pos":"conjunction"},"28:12":{"root":"كون","lemma":"كانَ","pos":"verb"},"28:13":{"root":"نزل","lemma":"مُنزِل","pos":"noun"},"29:1":{"root":null,"lemma":"إِن","pos":"negation"},"29:2":{"root":"كون","lemma":"كانَ","pos":"verb"},"29:3":{"root":null,"lemma":"إِلّا","pos":"restriction"},"29:4":{"root":"صيح","lemma":"صَيْحَة","pos":"noun"},"29:5":{"root":"وحد","lemma":"واحِدَة","pos":"noun"},"29:6":{"root":null,"lemma":"ف","pos":"resumption"},"29:8":{"root":"خمد","lemma":"خامِد","pos":"noun"},"30:1":{"root":"حسر","lemma":"حَسْرَة","pos":"noun"},"30:2":{"root":null,"lemma":"عَلَى","pos":"particle"},"30:3":{"root":"عبد","lemma":"عَبْد","pos":"noun"},"30:4":{"root":null,"lemma":"ما","pos":"negation"},"30:5":{"root":"أتي","lemma":"أَتَى","pos":"verb"},"30:6":{"root":null,"lemma":"مِن","pos":"particle"},"30:7":{"root":"رسل","lemma":"رَسُول","pos":"noun"},"30:8":{"root":null,"lemma":"إِلّا","pos":"restriction"},"30:9":{"root":"كون","lemma":"كانَ","pos":"verb"},"30:10":{"root":null,"lemma":"ب","pos":"particle"},"30:11":{"root":"هزأ","lemma":"اسْتُهْزِئَ","pos":"verb"},"31:1":{"root":null,"lemma":"أ","pos":"interrogative"},"31:2":{"root":"رأي","lemma":"رَأَى","pos":"verb"},"31:3":{"root":null,"lemma":"كَم","pos":"noun"},"31:4":{"root":"هلك","lemma":"أَهْلَكَ","pos":"verb"},"31:5":{"root":"قبل","lemma":"قَبْل","pos":"time adverb"},"31:6":{"root":null,"lemma":"مِن","pos":"particle"},"31:7":{"root":"قرن","lemma":"قَرْن","pos":"noun"},"31:8":{"root":null,"lemma":"أَنّ","pos":"particle"},"31:9":{"root":null,"lemma":"إِلَى","pos":"particle"},"31:10":{"root":null,"lemma":"لا","pos":"negation"},"31:11":{"root":"رجع","lemma":"رَجَعَ","pos":"verb"},"32:1":{"root":null,"lemma":"و","pos":"conjunction"},"32:2":{"root":"كلل","lemma":"كُلّ","pos":"noun"},"32:3":{"root":null,"lemma":"لَمّا","pos":"particle"},"32:4":{"root":"جمع","lemma":"جَمِيع","pos":"noun"},"32:5":{"root":null,"lemma":"لَدَى","pos":"location adverb"},"32:6":{"root":"حضر","lemma":"مُحْضَر","pos":"noun"},"33:1":{"root":"أيي","lemma":"آيَة","pos":"noun"},"33:2":{"root":null,"lemma":"ل","pos":"particle"},"33:3":{"root":"أرض","lemma":"أَرْض","pos":"noun"},"33:4":{"root":"موت","lemma":"مَيْتَة","pos":"noun"},"33:5":{"root":"حيي","lemma":"أَحْيا","pos":"verb"},"33:6":{"root":"خرج","lemma":"أَخْرَجَ","pos":"verb"},"33:7":{"root":null,"lemma":"مِن","pos":"particle"},"33:8":{"root":"حبب","lemma":"حَبّ","pos":"noun"},"33:9":{"root":null,"lemma":"ف","pos":"conjunction"},"33:10":{"root":"أكل","lemma":"أَكَلَ","pos":"verb"},"34:1":{"root":"جعل","lemma":"جَعَلَ","pos":"verb"},"34:2":{"root":null,"lemma":"فِي","pos":"particle"},"34:3":{"root":"جنن","lemma":"جَنَّة","pos":"noun"},"34:4":{"root":null,"lemma":"مِن","pos":"particle"},"34:5":{"root":"نخل","lemma":"نَخِيل","pos":"noun"},"34:6":{"root":"عنب","lemma":"عِنَب","pos":"noun"},"34:7":{"root":"فجر","lemma":"فُجِّرَتْ","pos":"verb"},"34:8":{"root":null,"lemma":"فِي","pos":"particle"},"34:9":{"root":null,"lemma":"مِن","pos":"particle"},"34:10":{"root":"عين","lemma":"عَيْن","pos":"noun"},"35:1":{"root":"أكل","lemma":"أَكَلَ","pos":"verb"},"35:2":{"root":null,"lemma":"مِن","pos":"particle"},"35:3":{"root":"ثمر","lemma":"ثَمَر","pos":"noun"},"35:4":{"root":null,"lemma":"و","pos":"conjunction"},"35:5":{"root":"عمل","lemma":"عَمِلَ","pos":"verb"},"35:6":{"root":"يدي","lemma":"يَد","pos":"noun"},"35:7":{"root":null,"lemma":"أ","pos":"interrogative"},"35:8":{"root":"شكر","lemma":"شَكَرَ","pos":"verb"},"36:1":{"root":"سبح","lemma":"سُبْحان","pos":"noun"},"36:2":{"root":null,"lemma":"الَّذِي","pos":"relative pronoun"},"36:3":{"root":"خلق","lemma":"خَلَقَ","pos":"verb"},"36:4":{"root":"زوج","lemma":"زَوْج","pos":"noun"},"36:5":{"root":"كلل","lemma":"كُلّ","pos":"noun"},"36:6":{"root":null,"lemma":"مِن","pos":"particle"},"36:7":{"root":"نبت","lemma":"أَنۢبَتَ","pos":"verb"},"36:8":{"root":"أرض","lemma":"أَرْض","pos":"noun"},"36:9":{"root":null,"lemma":"و","pos":"conjunction"},"36:10":{"root":"نفس","lemma":"نَفْس","pos":"noun"},"36:11":{"root":null,"lemma":"و","pos":"conjunction"},"36:12":{"root":null,"lemma":"لا","pos":"negation"},"36:13":{"root":"علم","lemma":"عَلِمَ","pos":"verb"},"37:1":{"root":"أيي","lemma":"آيَة","pos":"noun"},"37:2":{"root":null,"lemma":"ل","pos":"particle"},"37:3":{"root":"ليل","lemma":"لَيْل","pos":"noun"},"37:4":{"root":"سلخ","lemma":"نَسْلَخُ","pos":"verb"},"37:5":{"root":null,"lemma":"مِن","pos":"particle"},"37:6":{"root":"نهر","lemma":"نَهار","pos":"noun"},"37:7":{"root":null,"lemma":"ف","pos":"resumption"},"37:9":{"root":"ظلم","lemma":"مُظْلِم","pos":"noun"},"38:1":{"root":"شمس","lemma":"شَمْس","pos":"noun"},"38:2":{"root":"جري","lemma":"جَرَيْ","pos":"verb"},"38:3":{"root":"قرر","lemma":"مُسْتَقَرّ","pos":"noun"},"38:4":{"root":null,"lemma":"ل","pos":"particle"},"38:5":{"root":null,"lemma":"ذا","pos":"demonstrative"},"38:6":{"root":"قدر","lemma":"تَقْدِير","pos":"noun"},"38:7":{"root":"عزز","lemma":"عَزِيز","pos":"noun"},"38:8":{"root":"علم","lemma":"عَلِيم","pos":"noun"},"39:1":{"root":"قمر","lemma":"قَمَر","pos":"noun"},"39:2":{"root":"قدر","lemma":"قَدَّرَ","pos":"verb"},"39:3":{"root":"نزل","lemma":"مَنازِل","pos":"noun"},"39:4":{"root":null,"lemma":"حَتَّى","pos":"particle"},"39:5":{"root":"عود","lemma":"عادَ","pos":"verb"},"39:6":{"root":"عرجن","lemma":"عُرْجُون","pos":"noun"},"39:7":{"root":"قدم","lemma":"قَدِيم","pos":"noun"},"40:1":{"root":null,"lemma":"لا","pos":"negation"},"40:2":{"root":"شمس","lemma":"شَمْس","pos":"noun"},"40:3":{"root":"بغي","lemma":"يَنۢبَغِي","pos":"verb"},"40:4":{"root":null,"lemma":"ل","pos":"particle"},"40:5":{"root":null,"lemma":"أَن","pos":"particle"},"40:6":{"root":"درك","lemma":"أَدْرَكَ","pos":"verb"},"40:7":{"root":"قمر","lemma":"قَمَر","pos":"noun"},"40:8":{"root":null,"lemma":"و","pos":"conjunction"},"40:9":{"root":"ليل","lemma":"لَيْل","pos":"noun"},"40:10":{"root":"سبق","lemma":"سابِق","pos":"noun"},"40:11":{"root":"نهر","lemma":"نَهار","pos":"noun"},"40:12":{"root":"كلل","lemma":"كُلّ","pos":"noun"},"40:13":{"root":null,"lemma":"فِي","pos":"particle"},"40:14":{"root":"فلك","lemma":"فَلَك","pos":"noun"},"40:15":{"root":"سبح","lemma":"يَسْبَحُ","pos":"verb"},"41:1":{"root":"أيي","lemma":"آيَة","pos":"noun"},"41:2":{"root":null,"lemma":"ل","pos":"particle"},"41:3":{"root":null,"lemma":"أَنّ","pos":"particle"},"41:4":{"root":"حمل","lemma":"حَمَلَ","pos":"verb"},"41:5":{"root":"ذرر","lemma":"ذُرِّيَّة","pos":"noun"},"41:6":{"root":null,"lemma":"فِي","pos":"particle"},"41:7":{"root":"فلك","lemma":"فُلْك","pos":"noun"},"41:8":{"root":"شحن","lemma":"مَشْحُون","pos":"noun"},"42:1":{"root":"خلق","lemma":"خَلَقَ","pos":"verb"},"42:2":{"root":null,"lemma":"ل","pos":"particle"},"42:3":{"root":null,"lemma":"مِن","pos":"particle"},"42:4":{"root":"مثل","lemma":"مِثْل","pos":"noun"},"42:5":{"root":null,"lemma":"ما","pos":"relative pronoun"},"42:6":{"root":"ركب","lemma":"رَكِبَ","pos":"verb"},"43:1":{"root":null,"lemma":"و","pos":"conjunction"},"43:2":{"root":"شيأ","lemma":"شاءَ","pos":"verb"},"43:3":{"root":"غرق","lemma":"أُغْرِقُ","pos":"verb"},"43:4":{"root":null,"lemma":"ف","pos":"resumption"},"43:5":{"root":"صرخ","lemma":"صَرِيخ","pos":"noun"},"43:6":{"root":null,"lemma":"ل","pos":"particle"},"43:7":{"root":null,"lemma":"و","pos":"conjunction"},"43:9":{"root":"نقذ","lemma":"أَنقَذَ","pos":"verb"},"44:1":{"root":null,"lemma":"إِلّا","pos":"restriction"},"44:2":{"root":"رحم","lemma":"رَحْمَة","pos":"noun"},"44:3":{"root":null,"lemma":"مِن","pos":"particle"},"44:4":{"root":"متع","lemma":"مَتاع","pos":"noun"},"44:5":{"root":null,"lemma":"إِلَى","pos":"particle"},"44:6":{"root":"حين","lemma":"حِين","pos":"noun"},"45:1":{"root":null,"lemma":"و","pos":"conjunction"},"45:2":{"root":"قول","lemma":"قالَ","pos":"verb"},"45:3":{"root":null,"lemma":"ل","pos":"particle"},"45:4":{"root":"وقي","lemma":"اتَّقَى","pos":"verb"},"45:5":{"root":null,"lemma":"ما","pos":"relative pronoun"},"45:6":{"root":"بين","lemma":"بَيْن","pos":"location adverb"},"45:7":{"root":"يدي","lemma":"يَد","pos":"noun"},"45:8":{"root":null,"lemma":"و","pos":"conjunction"},"45:9":{"root":"خلف","lemma":"خَلْف","pos":"noun"},"45:10":{"root":null,"lemma":"لَعَلّ","pos":"particle"},"45:11":{"root":"رحم","lemma":"رَحِمَ","pos":"verb"},"46:1":{"root":null,"lemma":"و","pos":"conjunction"},"46:2":{"root":"أتي","lemma":"أَتَى","pos":"verb"},"46:3":{"root":null,"lemma":"مِن","pos":"particle"},"46:4":{"root":"أيي","lemma":"آيَة","pos":"noun"},"46:5":{"root":null,"lemma":"مِن","pos":"particle"},"46:6":{"root":"أيي","lemma":"آيَة","pos":"noun"},"46:7":{"root":"ربب","lemma":"رَبّ","pos":"noun"},"46:8":{"root":null,"lemma":"إِلّا","pos":"restriction"},"46:9":{"root":"كون","lemma":"كانَ","pos":"verb"},"46:10":{"root":null,"lemma":"عَن","pos":"particle"},"46:11":{"root":"عرض","lemma":"مُعْرِض","pos":"noun"},"47:1":{"root":null,"lemma":"و","pos":"conjunction"},"47:2":{"root":"قول","lemma":"قالَ","pos":"verb"},"47:3":{"root":null,"lemma":"ل","pos":"particle"},"47:4":{"root":"نفق","lemma":"أَنفَقَ","pos":"verb"},"47:5":{"root":null,"lemma":"مِن","pos":"particle"},"47:6":{"root":"رزق","lemma":"رَزَقَ","pos":"verb"},"47:7":{"root":"أله","lemma":"اللَّه","pos":"proper noun"},"47:8":{"root":"قول","lemma":"قالَ","pos":"verb"},"47:9":{"root":null,"lemma":"الَّذِي","pos":"relative pronoun"},"47:10":{"root":"كفر","lemma":"كَفَرَ","pos":"verb"},"47:11":{"root":null,"lemma":"ل","pos":"particle"},"47:12":{"root":"أمن","lemma":"آمَنَ","pos":"verb"},"47:13":{"root":"طعم","lemma":"أَطْعَمَ","pos":"verb"},"47:14":{"root":null,"lemma":"مَن","pos":"relative pronoun"},"47:15":{"root":null,"lemma":"لَو","pos":"conditional"},"47:16":{"root":"شيأ","lemma":"شاءَ","pos":"verb"},"47:17":{"root":"أله","lemma":"اللَّه","pos":"proper noun"},"47:18":{"root":"طعم","lemma":"أَطْعَمَ","pos":"verb"},"47:19":{"root":null,"lemma":"إِن","pos":"negation"},"47:21":{"root":null,"lemma":"إِلّا","pos":"restriction"},"47:22":{"root":null,"lemma":"فِي","pos":"particle"},"47:23":{"root":"ضلل","lemma":"ضَلال","pos":"noun"},"47:24":{"root":"بين","lemma":"مُبِين","pos":"noun"},"48:1":{"root":"قول","lemma":"قالَ","pos":"verb"},"48:2":{"root":null,"lemma":"مَتَى","pos":"interrogative"},"48:3":{"root":null,"lemma":"ه","pos":"particle"},"48:4":{"root":"وعد","lemma":"وَعْد","pos":"noun"},"48:5":{"root":null,"lemma":"إِن","pos":"conditional"},"48:6":{"root":"كون","lemma":"كانَ","pos":"verb"},"48:7":{"root":"صدق","lemma":"صادِق","pos":"noun"},"49:1":{"root":null,"lemma":"ما","pos":"negation"},"49:2":{"root":"نظر","lemma":"نَظَرَ","pos":"verb"},"49:3":{"root":null,"lemma":"إِلّا","pos":"restriction"},"49:4":{"root":"صيح","lemma":"صَيْحَة","pos":"noun"},"49:5":{"root":"وحد","lemma":"واحِدَة","pos":"noun"},"49:6":{"root":"أخذ","lemma":"أَخَذَ","pos":"verb"},"49:7":{"root":null,"lemma":"و","pos":"particle"},"49:8":{"root":"خصم","lemma":"اخْتَصَمُ","pos":"verb"},"50:1":{"root":null,"lemma":"ف","pos":"resumption"},"50:2":{"root":"طوع","lemma":"اسْتَطاعَ","pos":"verb"},"50:3":{"root":"وصي","lemma":"تَوْصِيَة","pos":"noun"},"50:4":{"root":null,"lemma":"و","pos":"conjunction"},"50:5":{"root":null,"lemma":"إِلَى","pos":"particle"},"50:6":{"root":"أهل","lemma":"أَهْل","pos":"noun"},"50:7":{"root":"رجع","lemma":"رَجَعَ","pos":"verb"},"51:1":{"root":"نفخ","lemma":"نَفَخَ","pos":"verb"},"51:2":{"root":null,"lemma":"فِي","pos":"particle"},"51:3":{"root":"صور","lemma":"صُور","pos":"noun"},"51:4":{"root":null,"lemma":"ف","pos":"conjunction"},"51:6":{"root":null,"lemma":"مِن","pos":"particle"},"51:7":{"root":"جدث","lemma":"أَجْداث","pos":"noun"},"51:8":{"root":null,"lemma":"إِلَى","pos":"particle"},"51:9":{"root":"ربب","lemma":"رَبّ","pos":"noun"},"51:10":{"root":"نسل","lemma":"يَنسِلُ","pos":"verb"},"52:1":{"root":"قول","lemma":"قالَ","pos":"verb"},"52:2":{"root":null,"lemma":"ي","pos":"vocative"},"52:3":{"root":null,"lemma":"مَن","pos":"relative pronoun"},"52:4":{"root":"بعث","lemma":"بَعَثَ","pos":"verb"},"52:5":{"root":null,"lemma":"مِن","pos":"particle"},"52:6":{"root":"رقد","lemma":"مَرْقَد","pos":"noun"},"52:7":{"root":null,"lemma":"ه","pos":"particle"},"52:8":{"root":null,"lemma":"ما","pos":"relative pronoun"},"52:9":{"root":"وعد","lemma":"وَعَدَ","pos":"verb"},"52:10":{"root":"رحم","lemma":"رَحْمٰن","pos":"noun"},"52:11":{"root":"صدق","lemma":"صَدَقَ","pos":"verb"},"52:12":{"root":"رسل","lemma":"مُرْسَل","pos":"noun"},"53:1":{"root":null,"lemma":"إِن","pos":"negation"},"53:2":{"root":"كون","lemma":"كانَ","pos":"verb"},"53:3":{"root":null,"lemma":"إِلّا","pos":"restriction"},"53:4":{"root":"صيح","lemma":"صَيْحَة","pos":"noun"},"53:5":{"root":"وحد","lemma":"واحِدَة","pos":"noun"},"53:6":{"root":null,"lemma":"ف","pos":"resumption"},"53:8":{"root":"جمع","lemma":"جَمِيع","pos":"noun"},"53:9":{"root":null,"lemma":"لَدَى","pos":"location adverb"},"53:10":{"root":"حضر","lemma":"مُحْضَر","pos":"noun"},"54:1":{"root":"يوم","lemma":"يَوْم","pos":"noun"},"54:2":{"root":null,"lemma":"لا","pos":"negation"},"54:3":{"root":"ظلم","lemma":"ظَلَمَ","pos":"verb"},"54:4":{"root":"نفس","lemma":"نَفْس","pos":"noun"},"54:5":{"root":"شيأ","lemma":"شَىْء","pos":"noun"},"54:6":{"root":null,"lemma":"و","pos":"conjunction"},"54:7":{"root":"جزي","lemma":"جَزَى","pos":"verb"},"54:8":{"root":null,"lemma":"إِلّا","pos":"restriction"},"54:9":{"root":null,"lemma":"ما","pos":"relative pronoun"},"54:10":{"root":"كون","lemma":"كانَ","pos":"verb"},"54:11":{"root":"عمل","lemma":"عَمِلَ","pos":"verb"},"55:1":{"root":null,"lemma":"إِنّ","pos":"particle"},"55:2":{"root":"صحب","lemma":"أَصْحاب","pos":"noun"},"55:3":{"root":"جنن","lemma":"جَنَّة","pos":"proper noun"},"55:4":{"root":"يوم","lemma":"يَوْم","pos":"noun"},"55:5":{"root":null,"lemma":"فِي","pos":"particle"},"55:6":{"root":"شغل","lemma":"شُغُل","pos":"noun"},"55:7":{"root":"فكه","lemma":"فاكِه","pos":"noun"},"56:2":{"root":"زوج","lemma":"زَوْج","pos":"noun"},"56:3":{"root":null,"lemma":"فِي","pos":"particle"},"56:4":{"root":"ظلل","lemma":"ظِلّ","pos":"noun"},"56:5":{"root":null,"lemma":"عَلَى","pos":"particle"},"56:6":{"root":"أرك","lemma":"أَرائِك","pos":"noun"},"56:7":{"root":"وكأ","lemma":"مُتَّكِئ","pos":"noun"},"57:1":{"root":null,"lemma":"ل","pos":"particle"},"57:2":{"root":null,"lemma":"فِي","pos":"particle"},"57:3":{"root":"فكه","lemma":"فاكِهَة","pos":"noun"},"57:4":{"root":null,"lemma":"و","pos":"conjunction"},"57:5":{"root":null,"lemma":"ما","pos":"relative pronoun"},"57:6":{"root":"دعو","lemma":"يَدَّعُ","pos":"verb"},"58:1":{"root":"سلم","lemma":"سَلام","pos":"noun"},"58:2":{"root":"قول","lemma":"قَوْل","pos":"noun"},"58:3":{"root":null,"lemma":"مِن","pos":"particle"},"58:4":{"root":"ربب","lemma":"رَبّ","pos":"noun"},"58:5":{"root":"رحم","lemma":"رَحِيم","pos":"noun"},"59:1":{"root":"ميز","lemma":"امْتازُ","pos":"verb"},"59:2":{"root":"يوم","lemma":"يَوْم","pos":"noun"},"59:3":{"root":"أيي","lemma":"أَيّ","pos":"noun"},"59:4":{"root":"جرم","lemma":"مُجْرِم","pos":"noun"},"60:1":{"root":null,"lemma":"أ","pos":"interrogative"},"60:2":{"root":"عهد","lemma":"عَهِدَ","pos":"verb"},"60:3":{"root":null,"lemma":"إِلَى","pos":"particle"},"60:4":{"root":"بني","lemma":"بُنَىّ","pos":"noun"},"60:5":{"root":"أدم","lemma":"آدَم","pos":"proper noun"},"60:6":{"root":null,"lemma":"أَن","pos":"interrogative"},"60:7":{"root":null,"lemma":"لا","pos":"prohibition"},"60:8":{"root":"عبد","lemma":"عَبَدَ","pos":"verb"},"60:9":{"root":"شطن","lemma":"شَيْطان","pos":"proper noun"},"60:10":{"root":null,"lemma":"إِنّ","pos":"particle"},"60:11":{"root":null,"lemma":"ل","pos":"particle"},"60:12":{"root":"عدو","lemma":"عَدُوّ","pos":"noun"},"60:13":{"root":"بين","lemma":"مُبِين","pos":"noun"},"61:1":{"root":null,"lemma":"و","pos":"conjunction"},"61:2":{"root":"عبد","lemma":"عَبَدَ","pos":"verb"},"61:3":{"root":null,"lemma":"ه","pos":"particle"},"61:4":{"root":"صرط","lemma":"صِراط","pos":"noun"},"61:5":{"root":"قوم","lemma":"مُسْتَقِيم","pos":"noun"},"62:1":{"root":null,"lemma":"و","pos":"conjunction"},"62:2":{"root":"ضلل","lemma":"أَضَلَّ","pos":"verb"},"62:3":{"root":null,"lemma":"مِن","pos":"particle"},"62:4":{"root":"جبل","lemma":"جِبِلَّة","pos":"noun"},"62:5":{"root":"كثر","lemma":"كَثِير","pos":"noun"},"62:6":{"root":null,"lemma":"أ","pos":"interrogative"},"62:7":{"root":"كون","lemma":"كانَ","pos":"verb"},"62:8":{"root":"عقل","lemma":"عَقَلُ","pos":"verb"},"63:1":{"root":null,"lemma":"ه","pos":"particle"},"63:2":{"root":null,"lemma":"جَهَنَّم","pos":"proper noun"},"63:3":{"root":null,"lemma":"الَّذِي","pos":"relative pronoun"},"63:4":{"root":"كون","lemma":"كانَ","pos":"verb"},"63:5":{"root":"وعد","lemma":"وَعَدَ","pos":"verb"},"64:1":{"root":"صلي","lemma":"يَصْلَى","pos":"verb"},"64:2":{"root":"يوم","lemma":"يَوْم","pos":"noun"},"64:3":{"root":null,"lemma":"ب","pos":"particle"},"64:4":{"root":"كون","lemma":"كانَ","pos":"verb"},"64:5":{"root":"كفر","lemma":"كَفَرَ","pos":"verb"},"65:1":{"root":"يوم","lemma":"يَوْم","pos":"noun"},"65:2":{"root":"ختم","lemma":"خَتَمَ","pos":"verb"},"65:3":{"root":null,"lemma":"عَلَى","pos":"particle"},"65:4":{"root":"فوه","lemma":"أَفْواه","pos":"noun"},"65:5":{"root":"كلم","lemma":"كَلَّمَ","pos":"verb"},"65:6":{"root":"يدي","lemma":"يَد","pos":"noun"},"65:7":{"root":"شهد","lemma":"شَهِدَ","pos":"verb"},"65:8":{"root":"رجل","lemma":"رِجْل","pos":"noun"},"65:9":{"root":null,"lemma":"ب","pos":"particle"},"65:10":{"root":"كون","lemma":"كانَ","pos":"verb"},"65:11":{"root":"كسب","lemma":"كَسَبَ","pos":"verb"},"66:1":{"root":null,"lemma":"و","pos":"conjunction"},"66:2":{"root":"شيأ","lemma":"شاءَ","pos":"verb"},"66:3":{"root":"طمس","lemma":"طُمِسَتْ","pos":"verb"},"66:4":{"root":null,"lemma":"عَلَى","pos":"particle"},"66:5":{"root":"عين","lemma":"عَيْن","pos":"noun"},"66:6":{"root":"سبق","lemma":"اسْتَبَقَ","pos":"verb"},"66:7":{"root":"صرط","lemma":"صِراط","pos":"noun"},"66:8":{"root":null,"lemma":"ف","pos":"resumption"},"66:9":{"root":"بصر","lemma":"أَبْصَرَ","pos":"verb"},"67:1":{"root":null,"lemma":"و","pos":"conjunction"},"67:2":{"root":"شيأ","lemma":"شاءَ","pos":"verb"},"67:3":{"root":"مسخ","lemma":"مَسَخْ","pos":"verb"},"67:4":{"root":null,"lemma":"عَلَى","pos":"particle"},"67:5":{"root":"كون","lemma":"مَكانَت","pos":"noun"},"67:6":{"root":null,"lemma":"ف","pos":"resumption"},"67:7":{"root":"طوع","lemma":"اسْتَطاعَ","pos":"verb"},"67:8":{"root":"مضي","lemma":"مُضِيّ","pos":"noun"},"67:9":{"root":null,"lemma":"و","pos":"conjunction"},"67:10":{"root":"رجع","lemma":"رَجَعَ","pos":"verb"},"68:1":{"root":null,"lemma":"و","pos":"conjunction"},"68:2":{"root":"عمر","lemma":"يُعَمَّرُ","pos":"verb"},"68:3":{"root":"نكس","lemma":"نُنَكِّسْ","pos":"verb"},"68:4":{"root":null,"lemma":"فِي","pos":"particle"},"68:5":{"root":"خلق","lemma":"خَلْق","pos":"noun"},"68:6":{"root":null,"lemma":"أ","pos":"interrogative"},"68:7":{"root":"عقل","lemma":"عَقَلُ","pos":"verb"},"69:1":{"root":null,"lemma":"و","pos":"conjunction"},"69:2":{"root":"علم","lemma":"عَلَّمَ","pos":"verb"},"69:3":{"root":"شعر","lemma":"شِعْر","pos":"noun"},"69:4":{"root":null,"lemma":"و","pos":"conjunction"},"69:5":{"root":"بغي","lemma":"يَنۢبَغِي","pos":"verb"},"69:6":{"root":null,"lemma":"ل","pos":"particle"},"69:7":{"root":null,"lemma":"إِن","pos":"negation"},"69:9":{"root":null,"lemma":"إِلّا","pos":"restriction"},"69:10":{"root":"ذكر","lemma":"ذِكْر","pos":"noun"},"69:11":{"root":"قرأ","lemma":"قُرْءان","pos":"proper noun"},"69:12":{"root":"بين","lemma":"مُبِين","pos":"noun"},"70:1":{"root":"نذر","lemma":"أَنذَرَ","pos":"verb"},"70:2":{"root":null,"lemma":"مَن","pos":"relative pronoun"},"70:3":{"root":"كون","lemma":"كانَ","pos":"verb"},"70:4":{"root":"حيي","lemma":"حَيّ","pos":"noun"},"70:5":{"root":"حقق","lemma":"حَقَّ","pos":"verb"},"70:6":{"root":"قول","lemma":"قَوْل","pos":"noun"},"70:7":{"root":null,"lemma":"عَلَى","pos":"particle"},"70:8":{"root":"كفر","lemma":"كافِر","pos":"noun"},"71:1":{"root":null,"lemma":"أ","pos":"interrogative"},"71:2":{"root":"رأي","lemma":"رَأَى","pos":"verb"},"71:3":{"root":null,"lemma":"أَنّ","pos":"particle"},"71:4":{"root":"خلق","lemma":"خَلَقَ","pos":"verb"},"71:5":{"root":null,"lemma":"ل","pos":"particle"},"71:6":{"root":null,"lemma":"مِن","pos":"particle"},"71:7":{"root":"عمل","lemma":"عَمِلَ","pos":"verb"},"71:8":{"root":"يدي","lemma":"يَد","pos":"noun"},"71:9":{"root":"نعم","lemma":"نَعَم","pos":"noun"},"71:10":{"root":null,"lemma":"ف","pos":"resumption"},"71:11":{"root":null,"lemma":"ل","pos":"particle"},"71:12":{"root":"ملك","lemma":"مالِك","pos":"noun"},"72:1":{"root":"ذلل","lemma":"ذُلِّلَتْ","pos":"verb"},"72:2":{"root":null,"lemma":"ل","pos":"particle"},"72:3":{"root":null,"lemma":"ف","pos":"resumption"},"72:4":{"root":"ركب","lemma":"رَكُوب","pos":"noun"},"72:5":{"root":null,"lemma":"و","pos":"conjunction"},"72:6":{"root":"أكل","lemma":"أَكَلَ","pos":"verb"},"73:1":{"root":null,"lemma":"و","pos":"conjunction"},"73:2":{"root":null,"lemma":"فِي","pos":"particle"},"73:3":{"root":"نفع","lemma":"مَنافِع","pos":"noun"},"73:4":{"root":"شرب","lemma":"مَشْرَب","pos":"noun"},"73:5":{"root":null,"lemma":"أ","pos":"interrogative"},"73:6":{"root":"شكر","lemma":"شَكَرَ","pos":"verb"},"74:1":{"root":"أخذ","lemma":"اتَّخَذَ","pos":"verb"},"74:2":{"root":null,"lemma":"مِن","pos":"particle"},"74:3":{"root":"دون","lemma":"دُون","pos":"noun"},"74:4":{"root":"أله","lemma":"اللَّه","pos":"proper noun"},"74:5":{"root":"أله","lemma":"إِلٰه","pos":"noun"},"74:6":{"root":null,"lemma":"لَعَلّ","pos":"particle"},"74:7":{"root":"نصر","lemma":"نَصَرَ","pos":"verb"},"75:1":{"root":null,"lemma":"لا","pos":"negation"},"75:2":{"root":"طوع","lemma":"اسْتَطاعَ","pos":"verb"},"75:3":{"root":"نصر","lemma":"نَصْر","pos":"noun"},"75:4":{"root":null,"lemma":"و","pos":"conjunction"},"75:5":{"root":null,"lemma":"ل","pos":"particle"},"75:6":{"root":"جند","lemma":"جُند","pos":"noun"},"75:7":{"root":"حضر","lemma":"مُحْضَر","pos":"noun"},"76:1":{"root":null,"lemma":"ف","pos":"resumption"},"76:2":{"root":"حزن","lemma":"يَحْزُن","pos":"verb"},"76:3":{"root":"قول","lemma":"قَوْل","pos":"noun"},"76:4":{"root":null,"lemma":"إِنّ","pos":"particle"},"76:5":{"root":"علم","lemma":"عَلِمَ","pos":"verb"},"76:6":{"root":null,"lemma":"ما","pos":"relative pronoun"},"76:7":{"root":"سرر","lemma":"أَسَرَّ","pos":"verb"},"76:8":{"root":null,"lemma":"و","pos":"conjunction"},"76:9":{"root":"علن","lemma":"أَعْلَن","pos":"verb"},"77:1":{"root":null,"lemma":"أ","pos":"interrogative"},"77:2":{"root":"رأي","lemma":"رَأَى","pos":"verb"},"77:3":{"root":"أنس","lemma":"إِنسان","pos":"noun"},"77:4":{"root":null,"lemma":"أَنّ","pos":"particle"},"77:5":{"root":"خلق","lemma":"خَلَقَ","pos":"verb"},"77:6":{"root":null,"lemma":"مِن","pos":"particle"},"77:7":{"root":"نطف","lemma":"نُطْفَة","pos":"noun"},"77:8":{"root":null,"lemma":"ف","pos":"resumption"},"77:10":{"root":"خصم","lemma":"خَصِيم","pos":"noun"},"77:11":{"root":"بين","lemma":"مُبِين","pos":"noun"},"78:1":{"root":"ضرب","lemma":"ضَرَبَ","pos":"verb"},"78:2":{"root":null,"lemma":"ل","pos":"particle"},"78:3":{"root":"مثل","lemma":"مَثَل","pos":"noun"},"78:4":{"root":"نسي","lemma":"نَسِيَ","pos":"verb"},"78:5":{"root":"خلق","lemma":"خَلْق","pos":"noun"},"78:6":{"root":"قول","lemma":"قالَ","pos":"verb"},"78:7":{"root":null,"lemma":"مَن","pos":"relative pronoun"},"78:8":{"root":"حيي","lemma":"أَحْيا","pos":"verb"},"78:9":{"root":"عظم","lemma":"عِظام","pos":"noun"},"78:10":{"root":null,"lemma":"و","pos":"particle"},"78:11":{"root":"رمم","lemma":"رَمِيم","pos":"noun"},"79:1":{"root":"قول","lemma":"قالَ","pos":"verb"},"79:2":{"root":"حيي","lemma":"أَحْيا","pos":"verb"},"79:3":{"root":null,"lemma":"الَّذِي","pos":"relative pronoun"},"79:4":{"root":"نشأ","lemma":"أَنشَأَ","pos":"verb"},"79:5":{"root":"أول","lemma":"أَوَّل","pos":"noun"},"79:6":{"root":"مرر","lemma":"مَرَّة","pos":"noun"},"79:7":{"root":null,"lemma":"و","pos":"conjunction"},"79:8":{"root":"كلل","lemma":"كُلّ","pos":"noun"},"79:9":{"root":"خلق","lemma":"خَلْق","pos":"noun"},"79:10":{"root":"علم","lemma":"عَلِيم","pos":"noun"},"80:1":{"root":null,"lemma":"الَّذِي","pos":"relative pronoun"},"80:2":{"root":"جعل","lemma":"جَعَلَ","pos":"verb"},"80:3":{"root":null,"lemma":"ل","pos":"particle"},"80:4":{"root":null,"lemma":"مِن","pos":"particle"},"80:5":{"root":"شجر","lemma":"شَجَر","pos":"noun"},"80:6":{"root":"خضر","lemma":"أَخْضَر","pos":"noun"},"80:7":{"root":"نور","lemma":"نار","pos":"noun"},"80:8":{"root":null,"lemma":"ف","pos":"conjunction"},"80:10":{"root":null,"lemma":"مِن","pos":"particle"},"80:11":{"root":"وقد","lemma":"أَوْقَدُ","pos":"verb"},"81:1":{"root":"ليس","lemma":"لَيْسَ","pos":"verb"},"81:2":{"root":null,"lemma":"الَّذِي","pos":"relative pronoun"},"81:3":{"root":"خلق","lemma":"خَلَقَ","pos":"verb"},"81:4":{"root":"سمو","lemma":"سَماء","pos":"noun"},"81:5":{"root":"أرض","lemma":"أَرْض","pos":"noun"},"81:6":{"root":"قدر","lemma":"قادِر","pos":"noun"},"81:7":{"root":null,"lemma":"عَلَى","pos":"particle"},"81:8":{"root":null,"lemma":"أَن","pos":"particle"},"81:9":{"root":"خلق","lemma":"خَلَقَ","pos":"verb"},"81:10":{"root":"مثل","lemma":"مِثْل","pos":"noun"},"81:11":{"root":null,"lemma":"بَلَى","pos":"answer"},"81:12":{"root":null,"lemma":"و","pos":"conjunction"},"81:13":{"root":"خلق","lemma":"خَلّاق","pos":"noun"},"81:14":{"root":"علم","lemma":"عَلِيم","pos":"noun"},"82:1":{"root":null,"lemma":"إِنّ","pos":"particle"},"82:2":{"root":"أمر","lemma":"أَمْر","pos":"noun"},"82:3":{"root":null,"lemma":"إِذا","pos":"time adverb"},"82:4":{"root":"رود","lemma":"أَرادَ","pos":"verb"},"82:5":{"root":"شيأ","lemma":"شَىْء","pos":"noun"},"82:6":{"root":null,"lemma":"أَن","pos":"particle"},"82:7":{"root":"قول","lemma":"قالَ","pos":"verb"},"82:8":{"root":null,"lemma":"ل","pos":"particle"},"82:9":{"root":"كون","lemma":"كانَ","pos":"verb"},"82:10":{"root":"كون","lemma":"كانَ","pos":"verb"},"83:1":{"root":"سبح","lemma":"سُبْحان","pos":"noun"},"83:2":{"root":null,"lemma":"الَّذِي","pos":"relative pronoun"},"83:3":{"root":"يدي","lemma":"يَد","pos":"noun"},"83:4":{"root":"ملك","lemma":"مَلَكُوت","pos":"noun"},"83:5":{"root":"كلل","lemma":"كُلّ","pos":"noun"},"83:6":{"root":"شيأ","lemma":"شَىْء","pos":"noun"},"83:7":{"root":null,"lemma":"و","pos":"conjunction"},"83:8":{"root":"رجع","lemma":"رَجَعَ","pos":"verb"}}